icrs/__init__.py
icrs/releaser/__init__.py
icrs/releaser/devremover.py
icrs/releaser/fullrelease.py
icrs/releaser/removecflags.py
icrs/releaser/setuptools_scm_versionfixer.py
icrs/releaser/versionreplacer.py
icrs/releaser/tests/__init__.py
icrs/releaser/tests/example_setup.txt
icrs/releaser/tests/test_devremover.py
icrs/releaser/tests/test_fullrelease.py
icrs/releaser/tests/test_removecflags.py
icrs/releaser/tests/test_setuptools_scm_versionfixer.py
icrs/releaser/tests/test_versionreplacer.py
icrs.releaser-1.3.0.dist-info/LICENSE
icrs.releaser-1.3.0.dist-info/METADATA
icrs.releaser-1.3.0.dist-info/WHEEL
icrs.releaser-1.3.0.dist-info/entry_points.txt
icrs.releaser-1.3.0.dist-info/top_level.txt
icrs.releaser-1.3.0.dist-info/RECORD
