Metadata-Version: 2.1
Name: icrs.releaser
Version: 1.3.0
Summary: zest.releaser/setuptools_scm plugin.
Home-page: https://github.com/jamadden/icrs.releaser
Author: Jason Madden
Author-email: jason@seecoresoftware.com
License: Apache
Project-URL: Documentation, https://icrsreleaser.readthedocs.io/en/latest/
Keywords: zest.releaser release automation setuptools_scm git
Classifier: Intended Audience :: Developers
Classifier: Natural Language :: English
Classifier: Operating System :: OS Independent
Classifier: Programming Language :: Python :: 3
Classifier: Programming Language :: Python :: 3.9
Classifier: Programming Language :: Python :: 3.10
Classifier: Programming Language :: Python :: 3.11
Classifier: Programming Language :: Python :: 3.12
Classifier: Programming Language :: Python :: 3.13
Classifier: Programming Language :: Python :: Implementation :: CPython
Classifier: Programming Language :: Python :: Implementation :: PyPy
Classifier: Development Status :: 1 - Planning
Requires-Python: >=3.9
License-File: LICENSE
Requires-Dist: zest.releaser>=9.1.1
Provides-Extra: docs
Requires-Dist: Sphinx; extra == "docs"
Requires-Dist: furo; extra == "docs"
Requires-Dist: sphinxcontrib-programoutput; extra == "docs"
Requires-Dist: coverage; extra == "docs"
Requires-Dist: zope.testrunner; extra == "docs"
Provides-Extra: recommended
Requires-Dist: zest.releaser[recommended]; extra == "recommended"
Provides-Extra: test
Requires-Dist: coverage; extra == "test"
Requires-Dist: zope.testrunner; extra == "test"
